requests_security_extra.py
requests_security_extra-0.dist-info/WHEEL
requests_security_extra-0.dist-info/METADATA
requests_security_extra-0.dist-info/RECORD
