Metadata-Version: 1.1
Name: requests-security-extra
Version: 0
Summary: A package used to detect installing 'requests[security]'
Home-page: https://github.com/psf/requests
Author: Seth Michael Larson
Author-email: sethmichaellarson@gmail.com
